README.md
lsm6ds3.py
lsm6ds3_micropython-0.0.3.dist-info/METADATA
lsm6ds3_micropython-0.0.3.dist-info/WHEEL
lsm6ds3_micropython-0.0.3.dist-info/licenses/LICENSE.txt
lsm6ds3_micropython-0.0.3.dist-info/RECORD
