Metadata-Version: 2.3
Name: lsm6ds3-micropython
Version: 0.0.3
Summary:  MicroPython device library for the LSM6DS3TR-C IMU
Project-URL: GitHub, https://www.github.com/pimoroni/lsm6ds3-micropython
Project-URL: Homepage, https://www.pimoroni.com
Author-email: Ryan <ryan@pimoroni.com>
License-File: LICENSE.txt
Classifier: License :: OSI Approved :: MIT License
